{
  "version": 1,
  "graph": {
    "id": "298ed696-1a12-4474-bca0-777ab503eddc",
    "nodes": [
      {
        "type": "ResourceNode",
        "id": "6d684fdc-da22-4781-a33b-edd6c030322b",
        "title": "Steel Sheet",
        "inputs": {},
        "outputs": {
          "material": {
            "id": "8e617fd0-9117-41d8-acd7-dbea3be4af92",
            "value": null
          }
        },
        "position": {
          "x": 251.87752794216735,
          "y": 136.89892433047908
        },
        "width": 200,
        "twoColumn": false,
        "resourceType": "input",
        "fields": {
          "origin": "",
          "inputQuantity": 0,
          "details": ""
        }
      },
      {
        "type": "ResourceNode",
        "id": "351e2787-61b9-4428-9a71-64a2ee6143a2",
        "title": "Paint",
        "inputs": {},
        "outputs": {
          "material": {
            "id": "d20e435b-5f39-46d7-b651-74b36a393c06",
            "value": null
          }
        },
        "position": {
          "x": 251.87752794216735,
          "y": 356.89893465196496
        },
        "width": 200,
        "twoColumn": false,
        "resourceType": "input",
        "fields": {
          "origin": "",
          "inputQuantity": 0,
          "details": ""
        }
      },
      {
        "type": "ResourceNode",
        "id": "21e9fefd-ec2a-49a1-8eca-12016fa4f454",
        "title": "Machine",
        "inputs": {},
        "outputs": {
          "machine_slot": {
            "id": "fee2c809-6ad6-43c6-b9cf-bee50ab63fba",
            "value": null
          }
        },
        "position": {
          "x": 71.87757700409566,
          "y": 996.8989502852965
        },
        "width": 200,
        "twoColumn": false,
        "resourceType": "machine",
        "fields": {
          "duration": "",
          "parameters": ""
        }
      },
      {
        "type": "ResourceNode",
        "id": "28cc590f-efb2-42b9-beb7-ed93511ceee7",
        "title": "Electricity",
        "inputs": {},
        "outputs": {
          "energy": {
            "id": "f99230ca-48e7-4609-aaa1-6db1a212ea32",
            "value": null
          }
        },
        "position": {
          "x": 311.87760562064784,
          "y": 996.8989502852965
        },
        "width": 200,
        "twoColumn": false,
        "resourceType": "energy",
        "fields": {
          "quantity": 0
        }
      },
      {
        "type": "ResourceNode",
        "id": "4d001cb3-eb1e-4618-af17-9660c33ffb21",
        "title": "Gáz (m3)",
        "inputs": {},
        "outputs": {
          "gas": {
            "id": "af479a51-b1a2-44ea-aea5-eaea2a911847",
            "value": null
          }
        },
        "position": {
          "x": 551.8776035749479,
          "y": 996.8989502852965
        },
        "width": 200,
        "twoColumn": false,
        "resourceType": "gas",
        "fields": {
          "quantity": 0
        }
      },
      {
        "type": "ResourceNode",
        "id": "bbd8961a-b6ad-4aa2-bb25-e4a93c585129",
        "title": "Víz (m3)",
        "inputs": {},
        "outputs": {
          "water": {
            "id": "a73ea9d5-2e04-48d5-9566-a1461cb854cd",
            "value": null
          }
        },
        "position": {
          "x": 791.8776628537523,
          "y": 996.8989502852965
        },
        "width": 200,
        "twoColumn": false,
        "resourceType": "water",
        "fields": {
          "quantity": 0
        }
      },
      {
        "type": "ResourceNode",
        "id": "00b227ab-3a3c-4974-9430-485ee9334265",
        "title": "Szolgáltatás",
        "inputs": {},
        "outputs": {
          "service": {
            "id": "5eeecf5d-78ad-4177-83d0-02a1a578607e",
            "value": null
          }
        },
        "position": {
          "x": 1031.8775994835478,
          "y": 996.8989502852965
        },
        "width": 200,
        "twoColumn": false,
        "resourceType": "service",
        "fields": {
          "duration": "",
          "parameters": ""
        }
      },
      {
        "type": "ResourceNode",
        "id": "6df4b8d1-c6eb-48e2-b981-9749b041f033",
        "title": "Ingatlan",
        "inputs": {},
        "outputs": {
          "property": {
            "id": "52a872dd-d432-43ab-89e2-9452ca1db73e",
            "value": null
          }
        },
        "position": {
          "x": 1271.8775361133435,
          "y": 996.8989502852965
        },
        "width": 200,
        "twoColumn": false,
        "resourceType": "property",
        "fields": {
          "duration": "",
          "parameters": ""
        }
      },
      {
        "type": "ProcessNode",
        "id": "e62a6c98-5d2f-4220-871e-84e5b95e353a",
        "title": "Process",
        "inputs": {
          "inputinstance_material": {
            "id": "156a94d8-e5c2-40ea-905d-93e3bb51a250",
            "value": null
          },
          "inputinstance_quantity": {
            "id": "9c752cb0-4a09-4b8e-90e7-36089701eea2",
            "value": null
          },
          "machineinstance_category": {
            "id": "de71b3e7-bd5e-4e95-8a39-6db2418c8012",
            "value": null
          },
          "machineinstance_quantity": {
            "id": "4ff32927-ebbb-4590-a001-735e1d2a8d21",
            "value": null
          },
          "serviceinstance_gas": {
            "id": "e5513910-8a33-4a80-96ef-75540a5cb086",
            "value": null
          },
          "serviceinstance_water": {
            "id": "e4554fec-76a3-4baa-b380-98ca23241e6f",
            "value": null
          },
          "serviceinstance_service": {
            "id": "b5eb7483-5b1a-458e-8fb0-a85ef55915cd",
            "value": null
          },
          "serviceinstance_property": {
            "id": "0d6fc512-c0d6-4880-a76a-01eb827f4aa7",
            "value": null
          },
          "input_material_input_3": {
            "id": "314ee45f-ec02-46ee-8c79-b0ca43baed09",
            "value": null
          },
          "input_material_input_4": {
            "id": "df09af07-9ae5-4984-8a3b-d1619210b5bb",
            "value": null
          }
        },
        "outputs": {
          "output_mainproduct": {
            "id": "e1ebb51e-32aa-4154-a5e9-f8249118cc27",
            "value": null
          },
          "output_byproduct": {
            "id": "d50e489a-c18a-428f-9974-6d8f81735123",
            "value": null
          },
          "output_product_output_3": {
            "id": "9ece0360-8ea4-4f58-aac3-e9a92f0d46c4",
            "value": null
          },
          "output_product_output_4": {
            "id": "c979f26f-c9cb-43ed-83a8-9cd3fa049f98",
            "value": null
          },
          "output_product_output_5": {
            "id": "0465811c-2fa7-47ac-9b9d-a1df84dc167b",
            "value": null
          }
        },
        "position": {
          "x": 671.8775565587196,
          "y": 467.89894317532713
        },
        "width": 200,
        "twoColumn": false,
        "details": "",
        "portMeta": {
          "inputinstance_material": {
            "side": "input",
            "flowType": "material",
            "fieldPath": "inputInstance.material"
          },
          "inputinstance_quantity": {
            "side": "input",
            "flowType": "material",
            "fieldPath": "inputInstance.quantity"
          },
          "machineinstance_category": {
            "side": "service",
            "flowType": "service",
            "fieldPath": "machineInstance.category"
          },
          "machineinstance_quantity": {
            "side": "service",
            "flowType": "service",
            "fieldPath": "machineInstance.quantity"
          },
          "serviceinstance_gas": {
            "side": "service",
            "flowType": "service",
            "fieldPath": "serviceInstance.gas"
          },
          "serviceinstance_water": {
            "side": "service",
            "flowType": "service",
            "fieldPath": "serviceInstance.water"
          },
          "serviceinstance_service": {
            "side": "service",
            "flowType": "service",
            "fieldPath": "serviceInstance.service"
          },
          "serviceinstance_property": {
            "side": "service",
            "flowType": "service",
            "fieldPath": "serviceInstance.property"
          },
          "input_material_input_3": {
            "side": "input",
            "flowType": "material"
          },
          "input_material_input_4": {
            "side": "input",
            "flowType": "material"
          },
          "output_mainproduct": {
            "side": "output",
            "flowType": "product",
            "fieldPath": "output.mainProduct"
          },
          "output_byproduct": {
            "side": "output",
            "flowType": "product",
            "fieldPath": "output.byproduct"
          },
          "output_product_output_3": {
            "side": "output",
            "flowType": "product"
          },
          "output_product_output_4": {
            "side": "output",
            "flowType": "product"
          },
          "output_product_output_5": {
            "side": "output",
            "flowType": "product"
          }
        }
      },
      {
        "type": "ProcessNode",
        "id": "88e46a51-2208-4002-9ec7-90b8da369740",
        "title": "Hulladékkezelés",
        "inputs": {
          "inputinstance_material": {
            "id": "79e1740f-3557-4963-a8e2-bc4ef99c6719",
            "value": null
          },
          "inputinstance_quantity": {
            "id": "3eeccf8f-1af1-439f-afd0-a45b22830c84",
            "value": null
          },
          "machineinstance_category": {
            "id": "f9573736-6b56-4d10-b095-04303701aca7",
            "value": null
          },
          "machineinstance_quantity": {
            "id": "abd18f36-ea8f-4032-90d1-6ebbb441c2e9",
            "value": null
          },
          "serviceinstance_gas": {
            "id": "2c5cc746-b37f-4f0f-8eb7-4a8e246286ee",
            "value": null
          },
          "serviceinstance_water": {
            "id": "65b52e1b-7df4-4969-a46a-83f490428dad",
            "value": null
          },
          "serviceinstance_service": {
            "id": "6f3090e7-8bbb-47b6-a1f6-6ab7b8359ea4",
            "value": null
          },
          "serviceinstance_property": {
            "id": "7683bd9d-cacf-4a43-8cc9-d1a28c84c4fe",
            "value": null
          }
        },
        "outputs": {
          "output_mainproduct": {
            "id": "ff924cc6-8a48-4153-af56-28e8afa030fd",
            "value": null
          },
          "output_byproduct": {
            "id": "fbdda490-983a-4148-93f0-6d0b58ec9533",
            "value": null
          }
        },
        "position": {
          "x": 1411.8777068014306,
          "y": 467.89894317532713
        },
        "width": 200,
        "twoColumn": false,
        "details": "",
        "portMeta": {
          "inputinstance_material": {
            "side": "input",
            "flowType": "material",
            "fieldPath": "inputInstance.material"
          },
          "inputinstance_quantity": {
            "side": "input",
            "flowType": "material",
            "fieldPath": "inputInstance.quantity"
          },
          "machineinstance_category": {
            "side": "service",
            "flowType": "service",
            "fieldPath": "machineInstance.category"
          },
          "machineinstance_quantity": {
            "side": "service",
            "flowType": "service",
            "fieldPath": "machineInstance.quantity"
          },
          "serviceinstance_gas": {
            "side": "service",
            "flowType": "service",
            "fieldPath": "serviceInstance.gas"
          },
          "serviceinstance_water": {
            "side": "service",
            "flowType": "service",
            "fieldPath": "serviceInstance.water"
          },
          "serviceinstance_service": {
            "side": "service",
            "flowType": "service",
            "fieldPath": "serviceInstance.service"
          },
          "serviceinstance_property": {
            "side": "service",
            "flowType": "service",
            "fieldPath": "serviceInstance.property"
          },
          "output_mainproduct": {
            "side": "output",
            "flowType": "product",
            "fieldPath": "output.mainProduct"
          },
          "output_byproduct": {
            "side": "output",
            "flowType": "product",
            "fieldPath": "output.byproduct"
          }
        }
      },
      {
        "type": "ResourceNode",
        "id": "8845b9ff-910a-48d7-abc1-a3e9d74db4fb",
        "title": "Főtermék",
        "inputs": {
          "product": {
            "id": "7d79c1cb-ec20-40cf-a68b-00cf00eda5aa",
            "value": null
          }
        },
        "outputs": {
          "output": {
            "id": "16d14464-3592-47bb-a237-c22f2f14bed4",
            "value": null
          }
        },
        "position": {
          "x": 1091.877615837524,
          "y": 232.89886386377373
        },
        "width": 200,
        "twoColumn": false,
        "resourceType": "output",
        "fields": {
          "outputKg": 1,
          "destination": "sarki boltba"
        }
      },
      {
        "type": "ResourceNode",
        "id": "d7bcd7ba-bd5d-4644-88a1-cece2d6615bf",
        "title": "Melléktermék",
        "inputs": {
          "product": {
            "id": "41ad938e-d1b0-48c4-a7cd-184e2e00ef8c",
            "value": null
          }
        },
        "outputs": {
          "output": {
            "id": "6a57991d-ac40-4c26-ab67-02dbd3990af0",
            "value": null
          }
        },
        "position": {
          "x": 1091.877615837524,
          "y": 404.898866090797
        },
        "width": 200,
        "twoColumn": false,
        "resourceType": "output",
        "fields": {
          "outputKg": 1,
          "destination": ""
        }
      },
      {
        "type": "ResourceNode",
        "id": "ad1135f4-12e0-443a-b580-7e906f33e1ac",
        "title": "Input 3",
        "inputs": {},
        "outputs": {
          "material": {
            "id": "c8cdfa0f-81bb-429d-92b9-90bf85d80bf1",
            "value": null
          }
        },
        "position": {
          "x": 251.87752794216735,
          "y": 576.8989603045769
        },
        "width": 200,
        "twoColumn": false,
        "resourceType": "input",
        "fields": {
          "origin": "",
          "inputQuantity": 0,
          "details": ""
        }
      },
      {
        "type": "ResourceNode",
        "id": "b1ea6e0c-8547-4321-93ce-76c5fcb30eaa",
        "title": "Output 4",
        "inputs": {
          "product": {
            "id": "9e309a67-baed-49a4-94d6-e5b9c2432fb8",
            "value": null
          }
        },
        "outputs": {
          "output": {
            "id": "f03ff6cf-3476-4578-940a-aa218e40196c",
            "value": null
          }
        },
        "position": {
          "x": 1091.877615837524,
          "y": 576.8988529866942
        },
        "width": 200,
        "twoColumn": false,
        "resourceType": "output",
        "fields": {
          "outputKg": 1,
          "destination": ""
        }
      },
      {
        "type": "ResourceNode",
        "id": "bdab8a28-e9d5-4ff8-b0d1-ad5ed4e27e20",
        "title": "Output 5",
        "inputs": {
          "product": {
            "id": "82d39774-651f-49ba-9764-e0699c2ef63b",
            "value": null
          }
        },
        "outputs": {
          "output": {
            "id": "f7cbf894-e559-4cb2-9508-7660a3f76a8a",
            "value": null
          }
        },
        "position": {
          "x": 1091.877615837524,
          "y": 748.8989318693481
        },
        "width": 200,
        "twoColumn": false,
        "resourceType": "output",
        "fields": {
          "outputKg": 1,
          "destination": ""
        }
      },
      {
        "type": "ResourceNode",
        "id": "6c98c897-a19e-4293-b8dc-655413f787f4",
        "title": "Input 4",
        "inputs": {},
        "outputs": {
          "material": {
            "id": "212a3119-27ed-4888-851f-1db1d2eefefd",
            "value": null
          }
        },
        "position": {
          "x": 251.87752794216735,
          "y": 796.8989552949367
        },
        "width": 200,
        "twoColumn": false,
        "resourceType": "input",
        "fields": {
          "origin": "",
          "inputQuantity": 0,
          "details": ""
        }
      }
    ],
    "connections": [
      {
        "id": "f64c609c-460b-4359-b475-0486e2a29023",
        "from": "8e617fd0-9117-41d8-acd7-dbea3be4af92",
        "to": "156a94d8-e5c2-40ea-905d-93e3bb51a250"
      },
      {
        "id": "a81d70d0-98f3-4e7c-ad2a-3451efec5818",
        "from": "d20e435b-5f39-46d7-b651-74b36a393c06",
        "to": "9c752cb0-4a09-4b8e-90e7-36089701eea2"
      },
      {
        "id": "08058e44-2a52-4a42-8649-d325453fdaad",
        "from": "fee2c809-6ad6-43c6-b9cf-bee50ab63fba",
        "to": "de71b3e7-bd5e-4e95-8a39-6db2418c8012"
      },
      {
        "id": "9df2f9e7-6ee0-45a1-b5bf-895c59bfdd15",
        "from": "f99230ca-48e7-4609-aaa1-6db1a212ea32",
        "to": "4ff32927-ebbb-4590-a001-735e1d2a8d21"
      },
      {
        "id": "fabc3a0e-bbc3-4a6c-afcd-217ce215ff77",
        "from": "af479a51-b1a2-44ea-aea5-eaea2a911847",
        "to": "e5513910-8a33-4a80-96ef-75540a5cb086"
      },
      {
        "id": "427876e1-d9df-4dc2-ac89-4f0cf18528a8",
        "from": "a73ea9d5-2e04-48d5-9566-a1461cb854cd",
        "to": "e4554fec-76a3-4baa-b380-98ca23241e6f"
      },
      {
        "id": "420971b3-c8ce-46c9-a271-b7f18596a084",
        "from": "5eeecf5d-78ad-4177-83d0-02a1a578607e",
        "to": "b5eb7483-5b1a-458e-8fb0-a85ef55915cd"
      },
      {
        "id": "387bd11a-02b0-437e-b782-35f738a2ef7f",
        "from": "52a872dd-d432-43ab-89e2-9452ca1db73e",
        "to": "0d6fc512-c0d6-4880-a76a-01eb827f4aa7"
      },
      {
        "id": "c3e5d9a3-1ccc-48fb-b5c1-51bc0dfdaec0",
        "from": "e1ebb51e-32aa-4154-a5e9-f8249118cc27",
        "to": "7d79c1cb-ec20-40cf-a68b-00cf00eda5aa"
      },
      {
        "id": "a25269ed-d221-4d2d-923c-637916ebb06b",
        "from": "d50e489a-c18a-428f-9974-6d8f81735123",
        "to": "41ad938e-d1b0-48c4-a7cd-184e2e00ef8c"
      },
      {
        "id": "f9e2ec0c-4419-4b68-91ab-007c91221cb9",
        "from": "6a57991d-ac40-4c26-ab67-02dbd3990af0",
        "to": "79e1740f-3557-4963-a8e2-bc4ef99c6719"
      },
      {
        "id": "54529d57-2097-452e-887e-387e93f2e2f2",
        "from": "c8cdfa0f-81bb-429d-92b9-90bf85d80bf1",
        "to": "314ee45f-ec02-46ee-8c79-b0ca43baed09"
      },
      {
        "id": "6806d158-c6e3-4dd6-9ad0-7a8dc33ddc1a",
        "from": "c979f26f-c9cb-43ed-83a8-9cd3fa049f98",
        "to": "9e309a67-baed-49a4-94d6-e5b9c2432fb8"
      },
      {
        "id": "d24130c1-d89b-41f0-ab2e-77c3068dd021",
        "from": "0465811c-2fa7-47ac-9b9d-a1df84dc167b",
        "to": "82d39774-651f-49ba-9764-e0699c2ef63b"
      },
      {
        "id": "94fe49e3-34f2-479a-bf33-d47c1e28190d",
        "from": "212a3119-27ed-4888-851f-1db1d2eefefd",
        "to": "df09af07-9ae5-4984-8a3b-d1619210b5bb"
      }
    ],
    "inputs": [],
    "outputs": [],
    "panning": {
      "x": 192.6734671649052,
      "y": -39.74652651974858
    },
    "scaling": 0.9952816874263325
  },
  "nodes": [
    {
      "id": "6d684fdc-da22-4781-a33b-edd6c030322b",
      "type": "ResourceNode",
      "title": "Steel Sheet",
      "position": {
        "x": 251.87752794216735,
        "y": 136.89892433047908
      },
      "resourceType": "input",
      "fields": {
        "origin": "",
        "inputQuantity": 0,
        "details": ""
      }
    },
    {
      "id": "351e2787-61b9-4428-9a71-64a2ee6143a2",
      "type": "ResourceNode",
      "title": "Paint",
      "position": {
        "x": 251.87752794216735,
        "y": 356.89893465196496
      },
      "resourceType": "input",
      "fields": {
        "origin": "",
        "inputQuantity": 0,
        "details": ""
      }
    },
    {
      "id": "21e9fefd-ec2a-49a1-8eca-12016fa4f454",
      "type": "ResourceNode",
      "title": "Machine",
      "position": {
        "x": 71.87757700409566,
        "y": 996.8989502852965
      },
      "resourceType": "machine",
      "fields": {
        "duration": "",
        "parameters": ""
      }
    },
    {
      "id": "28cc590f-efb2-42b9-beb7-ed93511ceee7",
      "type": "ResourceNode",
      "title": "Electricity",
      "position": {
        "x": 311.87760562064784,
        "y": 996.8989502852965
      },
      "resourceType": "energy",
      "fields": {
        "quantity": 0
      }
    },
    {
      "id": "4d001cb3-eb1e-4618-af17-9660c33ffb21",
      "type": "ResourceNode",
      "title": "Gáz (m3)",
      "position": {
        "x": 551.8776035749479,
        "y": 996.8989502852965
      },
      "resourceType": "gas",
      "fields": {
        "quantity": 0
      }
    },
    {
      "id": "bbd8961a-b6ad-4aa2-bb25-e4a93c585129",
      "type": "ResourceNode",
      "title": "Víz (m3)",
      "position": {
        "x": 791.8776628537523,
        "y": 996.8989502852965
      },
      "resourceType": "water",
      "fields": {
        "quantity": 0
      }
    },
    {
      "id": "00b227ab-3a3c-4974-9430-485ee9334265",
      "type": "ResourceNode",
      "title": "Szolgáltatás",
      "position": {
        "x": 1031.8775994835478,
        "y": 996.8989502852965
      },
      "resourceType": "service",
      "fields": {
        "duration": "",
        "parameters": ""
      }
    },
    {
      "id": "6df4b8d1-c6eb-48e2-b981-9749b041f033",
      "type": "ResourceNode",
      "title": "Ingatlan",
      "position": {
        "x": 1271.8775361133435,
        "y": 996.8989502852965
      },
      "resourceType": "property",
      "fields": {
        "duration": "",
        "parameters": ""
      }
    },
    {
      "id": "e62a6c98-5d2f-4220-871e-84e5b95e353a",
      "type": "ProcessNode",
      "title": "Process",
      "position": {
        "x": 671.8775565587196,
        "y": 467.89894317532713
      },
      "details": ""
    },
    {
      "id": "88e46a51-2208-4002-9ec7-90b8da369740",
      "type": "ProcessNode",
      "title": "Hulladékkezelés",
      "position": {
        "x": 1411.8777068014306,
        "y": 467.89894317532713
      },
      "details": ""
    },
    {
      "id": "8845b9ff-910a-48d7-abc1-a3e9d74db4fb",
      "type": "ResourceNode",
      "title": "Főtermék",
      "position": {
        "x": 1091.877615837524,
        "y": 232.89886386377373
      },
      "resourceType": "output",
      "fields": {
        "outputKg": 1,
        "destination": "sarki boltba"
      }
    },
    {
      "id": "d7bcd7ba-bd5d-4644-88a1-cece2d6615bf",
      "type": "ResourceNode",
      "title": "Melléktermék",
      "position": {
        "x": 1091.877615837524,
        "y": 404.898866090797
      },
      "resourceType": "output",
      "fields": {
        "outputKg": 1,
        "destination": ""
      }
    },
    {
      "id": "ad1135f4-12e0-443a-b580-7e906f33e1ac",
      "type": "ResourceNode",
      "title": "Input 3",
      "position": {
        "x": 251.87752794216735,
        "y": 576.8989603045769
      },
      "resourceType": "input",
      "fields": {
        "origin": "",
        "inputQuantity": 0,
        "details": ""
      }
    },
    {
      "id": "b1ea6e0c-8547-4321-93ce-76c5fcb30eaa",
      "type": "ResourceNode",
      "title": "Output 4",
      "position": {
        "x": 1091.877615837524,
        "y": 576.8988529866942
      },
      "resourceType": "output",
      "fields": {
        "outputKg": 1,
        "destination": ""
      }
    },
    {
      "id": "bdab8a28-e9d5-4ff8-b0d1-ad5ed4e27e20",
      "type": "ResourceNode",
      "title": "Output 5",
      "position": {
        "x": 1091.877615837524,
        "y": 748.8989318693481
      },
      "resourceType": "output",
      "fields": {
        "outputKg": 1,
        "destination": ""
      }
    },
    {
      "id": "6c98c897-a19e-4293-b8dc-655413f787f4",
      "type": "ResourceNode",
      "title": "Input 4",
      "position": {
        "x": 251.87752794216735,
        "y": 796.8989552949367
      },
      "resourceType": "input",
      "fields": {
        "origin": "",
        "inputQuantity": 0,
        "details": ""
      }
    }
  ],
  "view": {
    "scaling": 0.9952816874263325,
    "panning": {
      "x": 192.6734671649052,
      "y": -39.74652651974858
    }
  },
  "contact": {
    "email": "drahotab@gmail.com",
    "phone": "+3620802080"
  },
  "updatedAt": "2026-02-18T19:30:39.120Z",
  "id": "5b9b84a7-bec0-44c0-afa3-8d1a40786a7e",
  "createdAt": "2026-02-18T19:10:03.871Z",
  "owner": "17f4bae4e6f332b0",
  "lastUpdatedBy": "email:drahotab@gmail.com"
}